7e5ef9975678144bc711bcec7f34d81b	LOAD_GLOBAL
d8b5dbb683c70843f8c029171a7660aa	CALL_FUNCTION
8237ad091038b0c84405ee82623b3e67	STORE_FAST
dcec561d281f09c3d56f935a3da4ad36	LOAD_GLOBAL
d8fe5370c287ff961a18b2e84b3f4285	LOAD_CONST
a7fd298735505501c4ca52f7c310cb83	CALL_FUNCTION
6eab6ccac56207d81e5f02174b822d55	POP_TOP
7a59e9ef0aca4787976855cfe6f984b2	NOP
c609d0154440aa2b533558a4bb2be1fb	JUMP_ABSOLUTE
8a571d4b5442d73b4b3c2e82640e0b8c	LOAD_GLOBAL
a26291312777220b788f22783f6b3852	LOAD_GLOBAL
b407953d6d6cad876fbc797bc2042203	LOAD_CONST
0a7e56c941252d6d5a176c8f9e9fbbbd	CALL_FUNCTION
fadcf07fee8dda7bc277ce08ae669522	CALL_FUNCTION
46e5e8f05eee526ddbe3931ee46eb7f7	STORE_FAST
92827d6b2d44bb244bd0a49aab64f644	LOAD_FAST
b0ccade3f28220e2b3362ace4d980d15	LOAD_CONST
8bc0f1b5ce663d104da154e6f18eff4a	COMPARE_OP
9dbcf883b4431ee108519af287bf3310	POP_JUMP_IF_FALSE
6c8de520ec27e42683a1a24ab1fff1b8	LOAD_FAST
39ce8abf1cca01b59768ac6e8c3ceb16	LOAD_METHOD
eaf91e54c3a7589908e5bbf38cedabc3	CALL_METHOD
f225b6b49df2a4652b0b55f04dacbc73	POP_TOP
0fdfef3abb98cccc9b7e4914701692b0	JUMP_FORWARD
334af38e3c09351c854ae6e9bb58d0f3	LOAD_FAST
bcf4c96534c0330441b7bafac09bacef	LOAD_CONST
fd2c5b2419d72af38144ae1b1e972458	COMPARE_OP
3421e5ed65798ed1c6c34414a3a3d252	POP_JUMP_IF_FALSE
680526920670fc0902c234bae8cb6ff2	LOAD_FAST
ff0104d20de1202d031de93de52198e8	LOAD_METHOD
a11ad19e7fb48fcb297bda5f2d717f41	CALL_METHOD
26b4e62aaf7eedd5293fc344342a57c0	POP_TOP
78e7de268ddb1c88547cb22483acd38f	JUMP_FORWARD
2a902777482ec4a45dc87b3564aead30	LOAD_FAST
90ac4caccdb799d8f2c299b8c21c9512	LOAD_CONST
43e30c09f594c1b6a2c673dbd3cbb32c	COMPARE_OP
0680a623b19c2d75e1231d79941812a7	POP_JUMP_IF_FALSE
c3382e232804be32a81c23fcca6712d9	LOAD_FAST
7d74dd896c1626773a7c92a31c5fcaf3	LOAD_METHOD
1f228f78632547c5ad616c2367084f19	CALL_METHOD
85964e709c8f744bce3b42f61f730700	POP_TOP
b90df719f350fe0126b1c83b884b2e83	JUMP_FORWARD
0415d68fecba3a6f7e92cb0a38602fa2	LOAD_FAST
14f168c597acc5fc2d7deba319663909	LOAD_CONST
5ef2762a57ee5112b4457cf907ca68df	COMPARE_OP
73d64b01c10db1e9b532058f083395b0	POP_JUMP_IF_FALSE
ae336e63f5ce6fc09ebff63a0ce71d67	LOAD_FAST
093f135f44a812002389287bddc7aebd	LOAD_METHOD
9b208e12afce94b02e43ce127e861aec	CALL_METHOD
9e7d21a1d5fc9d37519f4075481a3e38	POP_TOP
bba49348be82de6f0418704147671f86	JUMP_FORWARD
0ab3bc7b6cfc4033bc65bcac94dc3c68	LOAD_FAST
bd223839179945a6af2dbf0571116d0b	LOAD_CONST
6ff824cbd75c42b0e8a54ea015702df1	COMPARE_OP
4780cab72afed7d81f4f8e80ad021ef0	POP_JUMP_IF_FALSE
8970ae1f4341ef52c3f063a5690a399f	LOAD_GLOBAL
fa7f1ab5e06bd8cff5906e12cd3a4bf9	CALL_FUNCTION
60333b13882024c11c79a9b2847c1722	POP_TOP
c86d4eb6e89add6db76a3def97d577cc	JUMP_FORWARD
4cb32cc892aa30a4ca26f9f13d11ca78	LOAD_GLOBAL
adb630fecb430371a9ca12d04ab6b5a7	LOAD_CONST
a31a706292002f7d1c791dc1e41362e2	CALL_FUNCTION
ee8527df632ef0850db9cb0a5f50b004	POP_TOP