bda6573167da55b27579f3029c5e355f	642e92efb79421734881b53e1e1b18b6	INPLACE_ADD		7.324324		None
48afe8c740e0d16414665758ea32d416	642e92efb79421734881b53e1e1b18b6	STORE_FAST		7.378378		x
e681d6784c45e2b6bfae2100cb26d253	c70daf247944fe3add32218f914c75a6	RETURN_VALUE		12.972973		None
564810b44d5590874526ffb42b14c9e3	c70daf247944fe3add32218f914c75a6	LOAD_FAST		11.702703		x
f478ca8e37d203cf1a577f0e81a20d0c	1e056d2b0ebd5c878c550da6ac5d3724	LOAD_FAST		9.486486		y
986e31d5e0a20a8025e615c39dd6e5e3	b4b147bc522828731f1a016bfa72c073	LOAD_FAST		6.000000		x
524511dc84ecdd19b21476433d3ddc5c	642e92efb79421734881b53e1e1b18b6	JUMP_FORWARD		7.432432		26
c85d6ed2f6767480205251b1fd8cf9ec	c70daf247944fe3add32218f914c75a6	BINARY_ADD		11.810811		None
bf3bce5667fc27d752b14cc1f1304a6e	b4b147bc522828731f1a016bfa72c073	LOAD_CONST		6.054054		1
dcf0e2cf5f3b5b3f6b4f7137a17049af	642e92efb79421734881b53e1e1b18b6	LOAD_CONST		7.270270		1
0f57cfb583b7d8331be853e324697911	1e056d2b0ebd5c878c550da6ac5d3724	STORE_FAST		9.540541		x
82464bac8b9020fa4e61f700bf7008f3	c70daf247944fe3add32218f914c75a6	LOAD_FAST		11.756757		y
5fddabf25b4acd9d644e17bdea440e0f	c70daf247944fe3add32218f914c75a6	STORE_FAST		11.864865		z
cf34e286a350a02e2eace33c5199847f	642e92efb79421734881b53e1e1b18b6	LOAD_FAST		7.216216		x
444095900d76df968ea4281d67eadebb	b4b147bc522828731f1a016bfa72c073	COMPARE_OP		6.108108		==
69887c03f40bfaf53c12bf970172b65e	b4b147bc522828731f1a016bfa72c073	POP_JUMP_IF_FALSE		6.162162		18
75924fd648476d2cbbb582f41a26ff2c	1e056d2b0ebd5c878c550da6ac5d3724	RETURN_VALUE		10.648649		None
984c282646fbb54863cdd53a39f035d2	c70daf247944fe3add32218f914c75a6	LOAD_FAST		12.918919		z
e889ed7552fabd5dc8f2d03e9ad217b2	1e056d2b0ebd5c878c550da6ac5d3724	LOAD_CONST		10.594595		None