8a571d4b5442d73b4b3c2e82640e0b8c	43fa7f58b7eac7ac872209342e62e8f1	LOAD_GLOBAL		138.128000		int
ee8527df632ef0850db9cb0a5f50b004	52c9a2647a3eaa9e295071ba521458f7	POP_TOP		150.976000		None
b407953d6d6cad876fbc797bc2042203	43fa7f58b7eac7ac872209342e62e8f1	LOAD_CONST		138.160000		Enter your choice: 
2a902777482ec4a45dc87b3564aead30	f0eaf559f89ca17022783964ebe9cdfd	LOAD_FAST		143.512000		choice
14f168c597acc5fc2d7deba319663909	13e5ebb0fa112fe1b31a1067962d74a7	LOAD_CONST		145.672000		4
6eab6ccac56207d81e5f02174b822d55	b4b147bc522828731f1a016bfa72c073	POP_TOP		136.096000		None
73d64b01c10db1e9b532058f083395b0	13e5ebb0fa112fe1b31a1067962d74a7	POP_JUMP_IF_FALSE		145.704000		100
9b208e12afce94b02e43ce127e861aec	cfe912f5cb3aa572bd1c9ae2a9b82207	CALL_METHOD		146.752000		0
fadcf07fee8dda7bc277ce08ae669522	43fa7f58b7eac7ac872209342e62e8f1	CALL_FUNCTION		138.192000		1
ff0104d20de1202d031de93de52198e8	044a23cadb567653eb51d4eb40acaa88	LOAD_METHOD		142.448000		searchContacts
bd223839179945a6af2dbf0571116d0b	5b5c37f4490273a893dd9a89d14ca062	LOAD_CONST		147.816000		5
7a59e9ef0aca4787976855cfe6f984b2	b4b147bc522828731f1a016bfa72c073	NOP		137.112000		None
43e30c09f594c1b6a2c673dbd3cbb32c	f0eaf559f89ca17022783964ebe9cdfd	COMPARE_OP		143.544000		==
60333b13882024c11c79a9b2847c1722	cde076c23203545591721c64b5c69963	POP_TOP		148.896000		None
7e5ef9975678144bc711bcec7f34d81b	b4b147bc522828731f1a016bfa72c073	LOAD_GLOBAL		135.000000		AddressBook
39ce8abf1cca01b59768ac6e8c3ceb16	f26dab9bf6a137c3b6782e562794c2f2	LOAD_METHOD		140.304000		addContacts
0fdfef3abb98cccc9b7e4914701692b0	f26dab9bf6a137c3b6782e562794c2f2	JUMP_FORWARD		140.352000		124
85964e709c8f744bce3b42f61f730700	f3c89b7be367aa4246f90aa007efe525	POP_TOP		144.624000		None
093f135f44a812002389287bddc7aebd	cfe912f5cb3aa572bd1c9ae2a9b82207	LOAD_METHOD		146.736000		displayContacts
9dbcf883b4431ee108519af287bf3310	43fa7f58b7eac7ac872209342e62e8f1	POP_JUMP_IF_FALSE		139.272000		46
b0ccade3f28220e2b3362ace4d980d15	43fa7f58b7eac7ac872209342e62e8f1	LOAD_CONST		139.240000		1
b90df719f350fe0126b1c83b884b2e83	f3c89b7be367aa4246f90aa007efe525	JUMP_FORWARD		144.640000		124
dcec561d281f09c3d56f935a3da4ad36	b4b147bc522828731f1a016bfa72c073	LOAD_GLOBAL		136.048000		print
7d74dd896c1626773a7c92a31c5fcaf3	f3c89b7be367aa4246f90aa007efe525	LOAD_METHOD		144.592000		modifyContacts
bba49348be82de6f0418704147671f86	cfe912f5cb3aa572bd1c9ae2a9b82207	JUMP_FORWARD		146.784000		124
3421e5ed65798ed1c6c34414a3a3d252	777669af68dbccabc30c3b6bcaa81825	POP_JUMP_IF_FALSE		141.416000		64
a26291312777220b788f22783f6b3852	43fa7f58b7eac7ac872209342e62e8f1	LOAD_GLOBAL		138.144000		input
f225b6b49df2a4652b0b55f04dacbc73	f26dab9bf6a137c3b6782e562794c2f2	POP_TOP		140.336000		None
c3382e232804be32a81c23fcca6712d9	f3c89b7be367aa4246f90aa007efe525	LOAD_FAST		144.576000		myBook
46e5e8f05eee526ddbe3931ee46eb7f7	43fa7f58b7eac7ac872209342e62e8f1	STORE_FAST		138.208000		choice
bcf4c96534c0330441b7bafac09bacef	777669af68dbccabc30c3b6bcaa81825	LOAD_CONST		141.384000		2
8970ae1f4341ef52c3f063a5690a399f	cde076c23203545591721c64b5c69963	LOAD_GLOBAL		148.864000		exit
fa7f1ab5e06bd8cff5906e12cd3a4bf9	cde076c23203545591721c64b5c69963	CALL_FUNCTION		148.880000		0
4cb32cc892aa30a4ca26f9f13d11ca78	52c9a2647a3eaa9e295071ba521458f7	LOAD_GLOBAL		150.928000		print
a7fd298735505501c4ca52f7c310cb83	b4b147bc522828731f1a016bfa72c073	CALL_FUNCTION		136.080000		1
d8fe5370c287ff961a18b2e84b3f4285	b4b147bc522828731f1a016bfa72c073	LOAD_CONST		136.064000		Enter 1. To Add Contacts 2. For Searching a Contact 3. For Modifying a Contact 4. To Display Contacts 5. To Exit
92827d6b2d44bb244bd0a49aab64f644	43fa7f58b7eac7ac872209342e62e8f1	LOAD_FAST		139.224000		choice
6c8de520ec27e42683a1a24ab1fff1b8	f26dab9bf6a137c3b6782e562794c2f2	LOAD_FAST		140.288000		myBook
334af38e3c09351c854ae6e9bb58d0f3	777669af68dbccabc30c3b6bcaa81825	LOAD_FAST		141.368000		choice
adb630fecb430371a9ca12d04ab6b5a7	52c9a2647a3eaa9e295071ba521458f7	LOAD_CONST		150.944000		Invalid Option. Try Again!
fd2c5b2419d72af38144ae1b1e972458	777669af68dbccabc30c3b6bcaa81825	COMPARE_OP		141.400000		==
1f228f78632547c5ad616c2367084f19	f3c89b7be367aa4246f90aa007efe525	CALL_METHOD		144.608000		0
26b4e62aaf7eedd5293fc344342a57c0	044a23cadb567653eb51d4eb40acaa88	POP_TOP		142.480000		None
90ac4caccdb799d8f2c299b8c21c9512	f0eaf559f89ca17022783964ebe9cdfd	LOAD_CONST		143.528000		3
9e7d21a1d5fc9d37519f4075481a3e38	cfe912f5cb3aa572bd1c9ae2a9b82207	POP_TOP		146.768000		None
a11ad19e7fb48fcb297bda5f2d717f41	044a23cadb567653eb51d4eb40acaa88	CALL_METHOD		142.464000		0
6ff824cbd75c42b0e8a54ea015702df1	5b5c37f4490273a893dd9a89d14ca062	COMPARE_OP		147.832000		==
0415d68fecba3a6f7e92cb0a38602fa2	13e5ebb0fa112fe1b31a1067962d74a7	LOAD_FAST		145.656000		choice
c86d4eb6e89add6db76a3def97d577cc	cde076c23203545591721c64b5c69963	JUMP_FORWARD		148.912000		124
0a7e56c941252d6d5a176c8f9e9fbbbd	43fa7f58b7eac7ac872209342e62e8f1	CALL_FUNCTION		138.176000		1
d8b5dbb683c70843f8c029171a7660aa	b4b147bc522828731f1a016bfa72c073	CALL_FUNCTION		135.016000		0
0680a623b19c2d75e1231d79941812a7	f0eaf559f89ca17022783964ebe9cdfd	POP_JUMP_IF_FALSE		143.560000		82
5ef2762a57ee5112b4457cf907ca68df	13e5ebb0fa112fe1b31a1067962d74a7	COMPARE_OP		145.688000		==
680526920670fc0902c234bae8cb6ff2	044a23cadb567653eb51d4eb40acaa88	LOAD_FAST		142.432000		myBook
78e7de268ddb1c88547cb22483acd38f	044a23cadb567653eb51d4eb40acaa88	JUMP_FORWARD		142.496000		124
0ab3bc7b6cfc4033bc65bcac94dc3c68	5b5c37f4490273a893dd9a89d14ca062	LOAD_FAST		147.800000		choice
a31a706292002f7d1c791dc1e41362e2	52c9a2647a3eaa9e295071ba521458f7	CALL_FUNCTION		150.960000		1
8237ad091038b0c84405ee82623b3e67	b4b147bc522828731f1a016bfa72c073	STORE_FAST		135.032000		myBook
c609d0154440aa2b533558a4bb2be1fb	282984b385d80166ba0d4f32a7843f53	JUMP_ABSOLUTE		137.992000		16
eaf91e54c3a7589908e5bbf38cedabc3	f26dab9bf6a137c3b6782e562794c2f2	CALL_METHOD		140.320000		0
8bc0f1b5ce663d104da154e6f18eff4a	43fa7f58b7eac7ac872209342e62e8f1	COMPARE_OP		139.256000		==
ae336e63f5ce6fc09ebff63a0ce71d67	cfe912f5cb3aa572bd1c9ae2a9b82207	LOAD_FAST		146.720000		myBook
4780cab72afed7d81f4f8e80ad021ef0	5b5c37f4490273a893dd9a89d14ca062	POP_JUMP_IF_FALSE		147.848000		116